classification_lib/__init__.py
classification_lib/plots.py
classification_lib-1.0.0.dist-info/LICENSE
classification_lib-1.0.0.dist-info/METADATA
classification_lib-1.0.0.dist-info/WHEEL
classification_lib-1.0.0.dist-info/top_level.txt
classification_lib-1.0.0.dist-info/RECORD
